databus/__init__.py
databus/api/__init__.py
databus/api/client.py
databus/api/models.py
databus/cli/__init__.py
databus/cli/main.py
databus/gtfs/__init__.py
databus/gtfs/analyzer.py
databus/gtfs/converter.py
databus/gtfs/processor.py
databus/gtfs/validator.py
databus/utils/__init__.py
databus/utils/config.py
databus/utils/exceptions.py
databus/utils/helpers.py
databus/validation/__init__.py
databus/validation/models.py
databus/validation/rules.py
databus-0.1.0.dist-info/METADATA
databus-0.1.0.dist-info/WHEEL
databus-0.1.0.dist-info/entry_points.txt
databus-0.1.0.dist-info/top_level.txt
databus-0.1.0.dist-info/RECORD
