Metadata-Version: 2.4
Name: databus
Version: 0.1.0
Summary: Python SDK and command-line toolkit for GTFS data processing, validation, and analysis. Provides programmatic access to Databús APIs, GTFS manipulation utilities, data conversion tools, and automated testing frameworks for transit data workflows and research applications.
Author-email: Fabián Abarca <ensinergia@gmail.com>
Project-URL: Homepage, https://github.com/fabianabarca/databus-py
Project-URL: Documentation, https://databus-py.readthedocs.io
Project-URL: Repository, https://github.com/fabianabarca/databus-py.git
Project-URL: Bug Tracker, https://github.com/fabianabarca/databus-py/issues
Keywords: gtfs,transit,transportation,data-processing,validation,api
Classifier: Development Status :: 3 - Alpha
Classifier: Intended Audience :: Developers
Classifier: Intended Audience :: Science/Research
Classifier: Operating System :: OS Independent
Classifier: Programming Language :: Python :: 3
Classifier: Programming Language :: Python :: 3.9
Classifier: Programming Language :: Python :: 3.10
Classifier: Programming Language :: Python :: 3.11
Classifier: Programming Language :: Python :: 3.12
Classifier: Topic :: Scientific/Engineering
Classifier: Topic :: Software Development :: Libraries :: Python Modules
Classifier: Topic :: Other/Nonlisted Topic
Requires-Python: >=3.9
Requires-Dist: requests>=2.31.0
Requires-Dist: pandas>=2.0.0
Requires-Dist: click>=8.0.0
Requires-Dist: pydantic>=2.0.0
Requires-Dist: rich>=13.0.0
Requires-Dist: gtfs-kit>=6.0.0
Requires-Dist: shapely>=2.0.0
Requires-Dist: geopandas>=0.14.0
Requires-Dist: pyarrow>=12.0.0
Provides-Extra: dev
Requires-Dist: pytest>=7.0.0; extra == "dev"
Requires-Dist: pytest-cov>=4.0.0; extra == "dev"
Requires-Dist: black>=23.0.0; extra == "dev"
Requires-Dist: isort>=5.12.0; extra == "dev"
Requires-Dist: flake8>=6.0.0; extra == "dev"
Requires-Dist: mypy>=1.5.0; extra == "dev"
Requires-Dist: pre-commit>=3.3.0; extra == "dev"
Provides-Extra: docs
Requires-Dist: mkdocs>=1.5.0; extra == "docs"
Requires-Dist: mkdocs-material>=9.0.0; extra == "docs"
Requires-Dist: mkdocstrings[python]>=0.22.0; extra == "docs"
Provides-Extra: test
Requires-Dist: pytest>=7.0.0; extra == "test"
Requires-Dist: pytest-cov>=4.0.0; extra == "test"
Requires-Dist: pytest-mock>=3.11.0; extra == "test"
Requires-Dist: responses>=0.23.0; extra == "test"
